simple_backups/__init__.py
simple_backups/backups.py
simple_backups/exceptions.py
simple_backups-0.3.3.dist-info/LICENSE
simple_backups-0.3.3.dist-info/METADATA
simple_backups-0.3.3.dist-info/WHEEL
simple_backups-0.3.3.dist-info/RECORD
