Metadata-Version: 2.1
Name: simple-backups
Version: 0.3.3
Summary: Simple backups library.
Home-page: https://github.com/luiscberrocal/simple-backups
License: MIT
Author: Luis C. Berrocal
Author-email: luis.berrocal.1942@gmail.com
Requires-Python: >=3.10,<3.13
Classifier: Development Status :: 2 - Pre-Alpha
Classifier: Intended Audience :: Developers
Classifier: License :: OSI Approved :: MIT License
Classifier: Natural Language :: English
Classifier: Programming Language :: Python :: 3
Classifier: Programming Language :: Python :: 3.10
Classifier: Programming Language :: Python :: 3.11
Classifier: Programming Language :: Python :: 3.12
Requires-Dist: mkdocstrings[python] (>=0.24.0,<0.25.0)
Requires-Dist: pydantic (>=2.5.3,<3.0.0)
